<?xml version="1.0" encoding="ISO-8859-1" standalone="no"?> 
<!DOCTYPE MAN SYSTEM "../../man.dtd">
<MAN>
  <LANGUAGE>fr</LANGUAGE>
  <TITLE>comp  </TITLE>
  <TYPE>Scilab Function  </TYPE>
  <DATE>April 1993  </DATE>
  <SHORT_DESCRIPTION name="comp">  pré-interprétation ou &quot;compilation&quot; de fonctions Scilab  </SHORT_DESCRIPTION>
  <CALLING_SEQUENCE>
  <CALLING_SEQUENCE_ITEM>comp(function [,opt])  </CALLING_SEQUENCE_ITEM>
  </CALLING_SEQUENCE>
  <PARAM>
 <PARAM_INDENT>
  <PARAM_ITEM>
  <PARAM_NAME>function  </PARAM_NAME>
  <PARAM_DESCRIPTION>
    : une fonction non &quot;compilée&quot; (type 11)
  </PARAM_DESCRIPTION> 
  </PARAM_ITEM>
  <PARAM_ITEM>
  <PARAM_NAME>opt  </PARAM_NAME>
  <PARAM_DESCRIPTION>
    : un entier valant 0 (par défaut) ou 1. 
  </PARAM_DESCRIPTION> 
  </PARAM_ITEM>
 </PARAM_INDENT>
  </PARAM>
  <DESCRIPTION>
  <P>
    &quot;compile&quot; la fonction <VERB>function</VERB>.
    Les fonctions &quot;compilées&quot; et interprétées sont équivalentes mais les
    fonctions &quot;compilées&quot; sont plus rapides.
    Les fonctions fournies dans les librairies standard de Scilab sont &quot;compilées&quot;.
  </P>
  <P>
    La commande :
  </P>
  <P>
    charge les fonctions du fichier <VERB>&apos;filename&apos;</VERB> et les &quot;compile&quot;.
  </P>
  <P>
    L&apos;option opt==1 est spécifique à des problèmes d&apos;analyse de code (voir macr2lst).
  </P>
  </DESCRIPTION>
  <ITEMIZE label='REMARQUES'>
  <P>
    les commandes 
  </P>
  <P>
    ne peuvent pas être &quot;compilées&quot;.
  </P>
  </ITEMIZE>
  <SEE_ALSO>
    <SEE_ALSO_ITEM> <LINK>deff</LINK> </SEE_ALSO_ITEM>     <SEE_ALSO_ITEM> <LINK>getf</LINK> </SEE_ALSO_ITEM>     <SEE_ALSO_ITEM> <LINK>whereis</LINK> </SEE_ALSO_ITEM>     <SEE_ALSO_ITEM> <LINK>macr2lst</LINK> </SEE_ALSO_ITEM>     <SEE_ALSO_ITEM> <LINK>lib</LINK> </SEE_ALSO_ITEM>
  </SEE_ALSO>
</MAN>
