<?xml version="1.0" encoding="ISO-8859-1" standalone="no"?>
<!DOCTYPE MAN SYSTEM "../../manrev.dtd">
<MAN>
  <LANGUAGE>eng</LANGUAGE>
  <TITLE>errclear</TITLE>
  <TYPE>Scilab Function</TYPE>
  <DATE>April 1993</DATE>
  <SHORT_DESCRIPTION name="errclear"> error clearing</SHORT_DESCRIPTION>
  <CALLING_SEQUENCE>
    <CALLING_SEQUENCE_ITEM>errclear([n])  </CALLING_SEQUENCE_ITEM>
  </CALLING_SEQUENCE>
  <DESCRIPTION>
    <P>
    clears the action (error-handler) connected to error of type  <VERB>n</VERB>.</P>
    <P>
    If <VERB>n</VERB> is positive, it is the number of the cleared error ; otherwise
    all errors are cleared (default case)</P>
  </DESCRIPTION>
  <SEE_ALSO>
    <SEE_ALSO_ITEM>
      <LINK>errcatch</LINK>
    </SEE_ALSO_ITEM>
    <SEE_ALSO_ITEM>
      <LINK>iserror</LINK>
    </SEE_ALSO_ITEM>
    <SEE_ALSO_ITEM>
      <LINK>lasterror</LINK>
    </SEE_ALSO_ITEM>
  </SEE_ALSO>
</MAN>
