<?xml version="1.0" encoding="ISO-8859-1" standalone="no"?> 
<!DOCTYPE MAN SYSTEM "../../manrev.dtd">
<MAN>
  <LANGUAGE>fr</LANGUAGE>
  <TITLE>cdfpoi  </TITLE>
  <TYPE>Scilab Function  </TYPE>
  <DATE>Dec 1997  </DATE>
  <SHORT_DESCRIPTION name="cdfpoi"> fonction de répartition de la distribution de Poisson  </SHORT_DESCRIPTION>
  <CALLING_SEQUENCE>
  <CALLING_SEQUENCE_ITEM>[P,Q]=cdfpoi(&quot;PQ&quot;,S,Xlam)  </CALLING_SEQUENCE_ITEM>
  <CALLING_SEQUENCE_ITEM>[S]=cdfpoi(&quot;S&quot;,Xlam,P,Q)  </CALLING_SEQUENCE_ITEM>
  <CALLING_SEQUENCE_ITEM>[Xlam]=cdfpoi(&quot;Xlam&quot;,P,Q,S);  </CALLING_SEQUENCE_ITEM>
  </CALLING_SEQUENCE>
  <PARAM>
 <PARAM_INDENT>
  <PARAM_ITEM>
  <PARAM_NAME>P,Q,S,Xlam  </PARAM_NAME>
  <PARAM_DESCRIPTION>
  <SP>
    : 4 vecteurs réels de même taille.
</SP>
  </PARAM_DESCRIPTION> 
  </PARAM_ITEM>
  <PARAM_ITEM>
  <PARAM_NAME>P,Q (Q=1-P)  </PARAM_NAME>
  <PARAM_DESCRIPTION>
  <SP>
    : La somme de  0 à S de la densité de Poisson. En entrée : [0,1].
</SP>
  </PARAM_DESCRIPTION> 
  </PARAM_ITEM>
  <PARAM_ITEM>
  <PARAM_NAME>S  </PARAM_NAME>
  <PARAM_DESCRIPTION>
  <SP>
    : Borne supérieure de la somme. En entrée : [0, +infini). En recherche : [0,1E300]
</SP>
  </PARAM_DESCRIPTION> 
  </PARAM_ITEM>
  <PARAM_ITEM>
  <PARAM_NAME>Xlam  </PARAM_NAME>
  <PARAM_DESCRIPTION>
  <SP>
    : Moyenne de la distribution. En entrée : [0, +infini). En recherche : [0,1E300]
</SP>
  </PARAM_DESCRIPTION> 
  </PARAM_ITEM>
 </PARAM_INDENT>
  </PARAM>
  <DESCRIPTION>
  <P>
    Étant donnés les autres, calcule un paramètre de la distribution de Poisson.
  </P>
  <P>
    La formule  26.4.21 de   Abramowitz  et  Stegun,   Handbook   of
    Mathematical Functions  (1966) est utilisée pour réduire le calcul de la fonction de répartition de la distribution à celle d&apos;une loi gamma incomplète.
  </P>
  <P>
  </P>
  <P>
    Tiré de la librairie DCDFLIB: Library of Fortran Routines for Cumulative Distribution
    Functions, Inverses, and Other Parameters (February, 1994)
    Barry W. Brown, James Lovato and Kathy Russell. The University of
    Texas.
  </P>
  </DESCRIPTION>
</MAN>
