<!--  Scicos

   Copyright (C) INRIA - METALAU Project <scicos@inria.fr>

  This program is free software; you can redistribute it and/or modify
  it under the terms of the GNU General Public License as published by
  the Free Software Foundation; either version 2 of the License, or
  (at your option) any later version.

  This program is distributed in the hope that it will be useful,
  but WITHOUT ANY WARRANTY; without even the implied warranty of
  MERCHANTABILITY or FITNESS FOR A PARTICULAR PURPOSE.  See the
  GNU General Public License for more details.

  You should have received a copy of the GNU General Public License
  along with this program; if not, write to the Free Software
  Foundation, Inc., 675 Mass Ave, Cambridge, MA 02139, USA.

  See the file ../license.txt
-->

<DATA flag="salso">

<FILE name='ABCD_Blocks' type='XML'>
<SEE_ALSO>

</SEE_ALSO>
</FILE>

<FILE name='ABSBLK_f' type='XML'>
<SEE_ALSO>

</SEE_ALSO>
</FILE>

<FILE name='ABS_VALUE' type='XML'>
<SEE_ALSO>

</SEE_ALSO>
</FILE>

<FILE name='AFFICH_f' type='XML'>
<SEE_ALSO>

</SEE_ALSO>
</FILE>

<FILE name='AFFICH_m' type='XML'>
<SEE_ALSO>

</SEE_ALSO>
</FILE>

<FILE name='ANDBLK' type='XML'>
<SEE_ALSO>

</SEE_ALSO>
</FILE>

<FILE name='ANDLOG_f' type='XML'>
<SEE_ALSO>

</SEE_ALSO>
</FILE>

<FILE name='AUTOMAT' type='XML'>
<SEE_ALSO>

</SEE_ALSO>
</FILE>

<FILE name='About_scicos' type='XML'>
  <SEE_ALSO>

  </SEE_ALSO>
</FILE>

<FILE name='BACKLASH' type='XML'>
<SEE_ALSO>

</SEE_ALSO>
</FILE>

<FILE name='BIGSOM_f' type='XML'>
<SEE_ALSO>

</SEE_ALSO>
</FILE>

<FILE name='BITCLEAR' type='XML'>
<SEE_ALSO>
<SEE_ALSO_ITEM> <LINK>BITSET</LINK> </SEE_ALSO_ITEM>
</SEE_ALSO>
</FILE>

<FILE name='BITSET' type='XML'>
<SEE_ALSO>
<SEE_ALSO_ITEM> <LINK>BITCLEAR</LINK> </SEE_ALSO_ITEM>
</SEE_ALSO>
</FILE>

<FILE name='BOUNCE' type='XML'>
<SEE_ALSO>

</SEE_ALSO>
</FILE>

<FILE name='BOUNCEXY' type='XML'>
<SEE_ALSO>

</SEE_ALSO>
</FILE>

<FILE name='BPLATFORM' type='XML'>
  <SEE_ALSO>

  </SEE_ALSO>
</FILE>

<FILE name='Bache' type='XML'>
<SEE_ALSO>

</SEE_ALSO>
</FILE>

<FILE name='Branching_pal' type='XML'>
<SEE_ALSO>

</SEE_ALSO>
</FILE>

<FILE name='CANIMXY' type='XML'>
<SEE_ALSO>
  <SEE_ALSO_ITEM><LINK>CANIMXY3D</LINK></SEE_ALSO_ITEM>
</SEE_ALSO>
</FILE>

<FILE name='CANIMXY3D' type='XML'>
<SEE_ALSO>
  <SEE_ALSO_ITEM><LINK>CANIMXY</LINK></SEE_ALSO_ITEM>
</SEE_ALSO>
</FILE>

<FILE name='CBLOCK' type='XML'>
<SEE_ALSO>

</SEE_ALSO>
</FILE>

<FILE name='CCS' type='XML'>
<SEE_ALSO>
<SEE_ALSO_ITEM> <LINK>CVS</LINK></SEE_ALSO_ITEM>
</SEE_ALSO>
</FILE>

<FILE name='CEVENTSCOPE' type='XML'>
<SEE_ALSO>

</SEE_ALSO>
</FILE>

<FILE name='CFSCOPE' type='XML'>
<SEE_ALSO>

</SEE_ALSO>
</FILE>

<FILE name='CLINDUMMY_f' type='XML'>
<SEE_ALSO>

</SEE_ALSO>
</FILE>

<FILE name='CLKFROM' type='XML'>
<SEE_ALSO>
<SEE_ALSO_ITEM><LINK>FROM</LINK></SEE_ALSO_ITEM>
</SEE_ALSO>
</FILE>

<FILE name='CLKGOTO' type='XML'>
<SEE_ALSO>
<SEE_ALSO_ITEM><LINK>GOTO</LINK></SEE_ALSO_ITEM>
</SEE_ALSO>
</FILE>

<FILE name='CLKGotoTagVisibility' type='XML'>
<SEE_ALSO>
<SEE_ALSO_ITEM><LINK>GotoTagVisibility</LINK></SEE_ALSO_ITEM>
</SEE_ALSO>
</FILE>

<FILE name='CLKINV_f' type='XML'>
<SEE_ALSO>

</SEE_ALSO>
</FILE>

<FILE name='CLKIN_f' type='XML'>
<SEE_ALSO>

</SEE_ALSO>
</FILE>

<FILE name='CLKOUTV_f' type='XML'>
<SEE_ALSO>

</SEE_ALSO>
</FILE>

<FILE name='CLKOUT_f' type='XML'>
<SEE_ALSO>

</SEE_ALSO>
</FILE>

<FILE name='CLKSOMV_f' type='XML'>
<SEE_ALSO>

</SEE_ALSO>
</FILE>

<FILE name='CLKSOM_f' type='XML'>
<SEE_ALSO>

</SEE_ALSO>
</FILE>

<FILE name='CLKSPLIT_f' type='XML'>
<SEE_ALSO>

</SEE_ALSO>
</FILE>

<FILE name='CLOCK_c' type='XML'>
<SEE_ALSO>
<SEE_ALSO_ITEM><LINK>EVTDLY_c</LINK></SEE_ALSO_ITEM>
</SEE_ALSO>
</FILE>

<FILE name='CLOCK_f' type='XML'>
<SEE_ALSO>

</SEE_ALSO>
</FILE>

<FILE name='CLR' type='XML'>
<SEE_ALSO>

</SEE_ALSO>
</FILE>

<FILE name='CLR_f' type='XML'>
<SEE_ALSO>

</SEE_ALSO>
</FILE>

<FILE name='CLSS' type='XML'>
<SEE_ALSO>

</SEE_ALSO>
</FILE>

<FILE name='CLSS_f' type='XML'>
<SEE_ALSO>

</SEE_ALSO>
</FILE>

<FILE name='CMAT3D' type='XML'>
<SEE_ALSO>
  <SEE_ALSO_ITEM><LINK>CMATVIEW</LINK></SEE_ALSO_ITEM>
</SEE_ALSO>
</FILE>

<FILE name='CMATVIEW' type='XML'>
<SEE_ALSO>
  <SEE_ALSO_ITEM><LINK>CMAT3D</LINK></SEE_ALSO_ITEM>
</SEE_ALSO>
</FILE>

<FILE name='CMSCOPE' type='XML'>
<SEE_ALSO>

</SEE_ALSO>
</FILE>

<FILE name='CONST' type='XML'>
<SEE_ALSO>

</SEE_ALSO>
</FILE>

<FILE name='CONSTRAINT_f' type='XML'>
<SEE_ALSO>

</SEE_ALSO>
</FILE>

<FILE name='CONST_f' type='XML'>
<SEE_ALSO>

</SEE_ALSO>
</FILE>

<FILE name='CONST_m' type='XML'>
<SEE_ALSO>

</SEE_ALSO>
</FILE>

<FILE name='CONVERT' type='XML'>
<SEE_ALSO>

</SEE_ALSO>
</FILE>

<FILE name='COSBLK_f' type='XML'>
<SEE_ALSO>

</SEE_ALSO>
</FILE>

<FILE name='CSCOPE' type='XML'>
<SEE_ALSO>
  <SEE_ALSO_ITEM><LINK>CMSCOPE</LINK></SEE_ALSO_ITEM>
</SEE_ALSO>
</FILE>

<FILE name='CSCOPXY' type='XML'>
<SEE_ALSO>
  <SEE_ALSO_ITEM><LINK>CSCOPXY3D</LINK></SEE_ALSO_ITEM>
</SEE_ALSO>
</FILE>

<FILE name='CSCOPXY3D' type='XML'>
<SEE_ALSO>
  <SEE_ALSO_ITEM><LINK>CSCOPXY</LINK></SEE_ALSO_ITEM>
</SEE_ALSO>
</FILE>

<FILE name='CUMSUM' type='XML'>
<SEE_ALSO>
<SEE_ALSO_ITEM><LINK>MATSUM</LINK></SEE_ALSO_ITEM>
</SEE_ALSO>
</FILE>

<FILE name='CURVE_c' type='XML'>
<SEE_ALSO>

</SEE_ALSO>
</FILE>

<FILE name='CURV_f' type='XML'>
<SEE_ALSO>
  <SEE_ALSO_ITEM><LINK>Sigbuilder </LINK></SEE_ALSO_ITEM>
</SEE_ALSO>
</FILE>

<FILE name='CVS' type='XML'>
<SEE_ALSO>
<SEE_ALSO_ITEM> <LINK>CCS</LINK></SEE_ALSO_ITEM>
</SEE_ALSO>
</FILE>

<FILE name='C_macros' type='XML'>
  <SEE_ALSO>

  </SEE_ALSO>
</FILE>

<FILE name='C_struct' type='XML'>
  <SEE_ALSO>

  </SEE_ALSO>
</FILE>

<FILE name='C_utils' type='XML'>
  <SEE_ALSO>

  </SEE_ALSO>
</FILE>

<FILE name='Capacitor' type='XML'>
<SEE_ALSO>

</SEE_ALSO>
</FILE>

<FILE name='ConstantVoltage' type='XML'>
<SEE_ALSO>

</SEE_ALSO>
</FILE>

<FILE name='Context' type='XML'>
  <SEE_ALSO>

  </SEE_ALSO>
</FILE>

<FILE name='Counter' type='XML'>
<SEE_ALSO>
<SEE_ALSO_ITEM><LINK>Modulo_Count</LINK></SEE_ALSO_ITEM>
</SEE_ALSO>
</FILE>

<FILE name='CurrentSensor' type='XML'>
<SEE_ALSO>

</SEE_ALSO>
</FILE>

<FILE name='DEADBAND' type='XML'>
<SEE_ALSO>

</SEE_ALSO>
</FILE>

<FILE name='DEBUG_SCICOS' type='XML'>
<SEE_ALSO>

</SEE_ALSO>
</FILE>

<FILE name='DELAYV_f' type='XML'>
<SEE_ALSO>

</SEE_ALSO>
</FILE>

<FILE name='DELAY_f' type='XML'>
<SEE_ALSO>

</SEE_ALSO>
</FILE>

<FILE name='DEMUX' type='XML'>
<SEE_ALSO>

</SEE_ALSO>
</FILE>

<FILE name='DEMUX_f' type='XML'>
<SEE_ALSO>

</SEE_ALSO>
</FILE>

<FILE name='DERIV' type='XML'>
<SEE_ALSO>

</SEE_ALSO>
</FILE>

<FILE name='DFLIPFLOP' type='XML'>
<SEE_ALSO>
<SEE_ALSO_ITEM><LINK>DLATCH</LINK></SEE_ALSO_ITEM>
<SEE_ALSO_ITEM><LINK>SRFLIPFLOP</LINK></SEE_ALSO_ITEM>
<SEE_ALSO_ITEM><LINK>JKFLIPFLOP</LINK></SEE_ALSO_ITEM>
</SEE_ALSO>
</FILE>

<FILE name='DIFF_f' type='XML'>
<SEE_ALSO>

</SEE_ALSO>
</FILE>

<FILE name='DLATCH' type='XML'>
<SEE_ALSO>
<SEE_ALSO_ITEM><LINK>DFLIPFLOP</LINK></SEE_ALSO_ITEM>
<SEE_ALSO_ITEM><LINK>SRFLIPFLOP</LINK></SEE_ALSO_ITEM>
<SEE_ALSO_ITEM><LINK>JKFLIPFLOP</LINK></SEE_ALSO_ITEM>
</SEE_ALSO>
</FILE>

<FILE name='DLR' type='XML'>
<SEE_ALSO>

</SEE_ALSO>
</FILE>

<FILE name='DLRADAPT_f' type='XML'>
<SEE_ALSO>

</SEE_ALSO>
</FILE>

<FILE name='DLR_f' type='XML'>
<SEE_ALSO>

</SEE_ALSO>
</FILE>

<FILE name='DLSS' type='XML'>
<SEE_ALSO>

</SEE_ALSO>
</FILE>

<FILE name='DLSS_f' type='XML'>
<SEE_ALSO>

</SEE_ALSO>
</FILE>

<FILE name='DOLLAR' type='XML'>
<SEE_ALSO>

</SEE_ALSO>
</FILE>

<FILE name='DOLLAR_f' type='XML'>
<SEE_ALSO>

</SEE_ALSO>
</FILE>

<FILE name='DOLLAR_m' type='XML'>
<SEE_ALSO>

</SEE_ALSO>
</FILE>

<FILE name='DemoBlocks_pal' type='XML'>
<SEE_ALSO>

</SEE_ALSO>
</FILE>

<FILE name='Diode' type='XML'>
<SEE_ALSO>

</SEE_ALSO>
</FILE>

<FILE name='EDGETRIGGER' type='XML'>
<SEE_ALSO>

</SEE_ALSO>
</FILE>

<FILE name='EDGE_TRIGGER' type='XML'>
<SEE_ALSO>

</SEE_ALSO>
</FILE>

<FILE name='ENDBLK' type='XML'>
  <SEE_ALSO>
  <SEE_ALSO_ITEM><LINK>END_c</LINK></SEE_ALSO_ITEM>
  </SEE_ALSO>
</FILE>

<FILE name='END_c' type='XML'>
  <SEE_ALSO>
  <SEE_ALSO_ITEM><LINK>ENDBLK</LINK></SEE_ALSO_ITEM>
  </SEE_ALSO>
</FILE>

<FILE name='ESELECT_f' type='XML'>
<SEE_ALSO>



</SEE_ALSO>
</FILE>

<FILE name='EVTDLY_c' type='XML'>
<SEE_ALSO>
<SEE_ALSO_ITEM><LINK>CLOCK_c</LINK></SEE_ALSO_ITEM>
</SEE_ALSO>
</FILE>

<FILE name='EVTDLY_f' type='XML'>
<SEE_ALSO>



</SEE_ALSO>
</FILE>

<FILE name='EVTGEN_f' type='XML'>
<SEE_ALSO>



</SEE_ALSO>
</FILE>

<FILE name='EVTVARDLY' type='XML'>
<SEE_ALSO>



</SEE_ALSO>
</FILE>

<FILE name='EXPBLK_f' type='XML'>
<SEE_ALSO>



</SEE_ALSO>
</FILE>

<FILE name='EXPBLK_m' type='XML'>
<SEE_ALSO>

</SEE_ALSO>
</FILE>

<FILE name='EXPRESSION' type='XML'>
<SEE_ALSO>



</SEE_ALSO>
</FILE>

<FILE name='EXTRACT' type='XML'>
<SEE_ALSO>
<SEE_ALSO_ITEM><LINK>EXTTRI</LINK></SEE_ALSO_ITEM>
</SEE_ALSO>
</FILE>

<FILE name='EXTRACTBITS' type='XML'>
<SEE_ALSO>
<SEE_ALSO_ITEM> <LINK>BITSET</LINK> </SEE_ALSO_ITEM>
<SEE_ALSO_ITEM> <LINK>BITCLEAR</LINK> </SEE_ALSO_ITEM>
</SEE_ALSO>
</FILE>

<FILE name='EXTRACTOR' type='XML'>
<SEE_ALSO>



</SEE_ALSO>
</FILE>

<FILE name='EXTTRI' type='XML'>
<SEE_ALSO>
<SEE_ALSO_ITEM><LINK>EXTRACT</LINK></SEE_ALSO_ITEM>
</SEE_ALSO>
</FILE>

<FILE name='Electrical_pal' type='XML'>
<SEE_ALSO>



</SEE_ALSO>
</FILE>

<FILE name='Events_pal' type='XML'>
<SEE_ALSO>

</SEE_ALSO>
</FILE>

<FILE name='Extract_Activation' type='XML'>
<SEE_ALSO>

</SEE_ALSO>
</FILE>

<FILE name='FROM' type='XML'>
<SEE_ALSO>
<SEE_ALSO_ITEM> <LINK>GOTO</LINK> </SEE_ALSO_ITEM>
<SEE_ALSO_ITEM> <LINK>GotoTagVisibility</LINK> </SEE_ALSO_ITEM>
</SEE_ALSO>
</FILE>

<FILE name='FROMMO' type='XML'>
<SEE_ALSO>
<SEE_ALSO_ITEM><LINK>FROM</LINK></SEE_ALSO_ITEM>
</SEE_ALSO>
</FILE>

<FILE name='FROMWSB' type='XML'>
  <SEE_ALSO>
   <SEE_ALSO_ITEM> <LINK>TOWS_c</LINK> </SEE_ALSO_ITEM>
   <SEE_ALSO_ITEM><LINK>FROMWS_c</LINK></SEE_ALSO_ITEM>
  </SEE_ALSO>
</FILE>

<FILE name='FROMWS_c' type='XML'>
  <SEE_ALSO>
   <SEE_ALSO_ITEM> <LINK>TOWS_c</LINK> </SEE_ALSO_ITEM>
   <SEE_ALSO_ITEM><LINK>FROMWSB</LINK></SEE_ALSO_ITEM>
  </SEE_ALSO>
</FILE>

<FILE name='FSV_f' type='XML'>
<SEE_ALSO>

</SEE_ALSO>
</FILE>

<FILE name='GAINBLK' type='XML'>
<SEE_ALSO>
<SEE_ALSO_ITEM><LINK>INTMUL</LINK></SEE_ALSO_ITEM>
<SEE_ALSO_ITEM><LINK>MATMUL</LINK></SEE_ALSO_ITEM>
</SEE_ALSO>
</FILE>

<FILE name='GAINBLK_f' type='XML'>
<SEE_ALSO>

</SEE_ALSO>
</FILE>

<FILE name='GAIN_f' type='XML'>
<SEE_ALSO>

</SEE_ALSO>
</FILE>

<FILE name='GENERAL_f' type='XML'>
<SEE_ALSO>

</SEE_ALSO>
</FILE>

<FILE name='GENSIN_f' type='XML'>
<SEE_ALSO>

</SEE_ALSO>
</FILE>

<FILE name='GENSQR_f' type='XML'>
<SEE_ALSO>

</SEE_ALSO>
</FILE>

<FILE name='GOTO' type='XML'>
<SEE_ALSO>
<SEE_ALSO_ITEM><LINK>FROM</LINK></SEE_ALSO_ITEM>
<SEE_ALSO_ITEM><LINK>GotoTagVisibility</LINK></SEE_ALSO_ITEM>
</SEE_ALSO>
</FILE>

<FILE name='GOTOMO' type='XML'>
<SEE_ALSO>
<SEE_ALSO_ITEM><LINK>GOTO</LINK></SEE_ALSO_ITEM>
</SEE_ALSO>
</FILE>

<FILE name='GotoTagVisibility' type='XML'>
<SEE_ALSO>
<SEE_ALSO_ITEM><LINK>GOTO</LINK></SEE_ALSO_ITEM>
<SEE_ALSO_ITEM><LINK>FROM</LINK></SEE_ALSO_ITEM>
</SEE_ALSO>
</FILE>

<FILE name='GotoTagVisibilityMO' type='XML'>
<SEE_ALSO>
<SEE_ALSO_ITEM><LINK>GotoTagVisibility</LINK></SEE_ALSO_ITEM>
</SEE_ALSO>
</FILE>

<FILE name='Ground' type='XML'>
<SEE_ALSO>

</SEE_ALSO>
</FILE>

<FILE name='Gyrator' type='XML'>
  <SEE_ALSO>

  </SEE_ALSO>
</FILE>

<FILE name='HALT_f' type='XML'>
<SEE_ALSO>

</SEE_ALSO>
</FILE>

<FILE name='HYSTHERESIS' type='XML'>
<SEE_ALSO>

</SEE_ALSO>
</FILE>

<FILE name='IFTHEL_f' type='XML'>
<SEE_ALSO>

</SEE_ALSO>
</FILE>

<FILE name='IMPSPLIT_f' type='XML'>
<SEE_ALSO>

</SEE_ALSO>
</FILE>

<FILE name='INIMPL_f' type='XML'>
<SEE_ALSO>

</SEE_ALSO>
</FILE>

<FILE name='INTEGRAL' type='XML'>
<SEE_ALSO>

</SEE_ALSO>
</FILE>

<FILE name='INTEGRAL_f' type='XML'>
<SEE_ALSO>

</SEE_ALSO>
</FILE>

<FILE name='INTEGRAL_m' type='XML'>
<SEE_ALSO>

</SEE_ALSO>
</FILE>

<FILE name='INTMUL' type='XML'>
<SEE_ALSO>
<SEE_ALSO_ITEM> <LINK>MATMUL</LINK> </SEE_ALSO_ITEM>
</SEE_ALSO>
</FILE>

<FILE name='INTRP2BLK_f' type='XML'>
<SEE_ALSO>

</SEE_ALSO>
</FILE>

<FILE name='INTRPLBLK_f' type='XML'>
<SEE_ALSO>



</SEE_ALSO>
</FILE>

<FILE name='INVBLK' type='XML'>
<SEE_ALSO>

</SEE_ALSO>
</FILE>

<FILE name='INVBLK_f' type='XML'>
<SEE_ALSO>

</SEE_ALSO>
</FILE>

<FILE name='IN_f' type='XML'>
<SEE_ALSO>

</SEE_ALSO>
</FILE>

<FILE name='ISELECT_f' type='XML'>
<SEE_ALSO>

</SEE_ALSO>
</FILE>

<FILE name='ISELECT_m' type='XML'>
<SEE_ALSO>

</SEE_ALSO>
</FILE>

<FILE name='IdealTransformer' type='XML'>
<SEE_ALSO>

</SEE_ALSO>
</FILE>

<FILE name='Inductor' type='XML'>
<SEE_ALSO>

</SEE_ALSO>
</FILE>

<FILE name='Integer_pal' type='XML'>
<SEE_ALSO>

</SEE_ALSO>
</FILE>

<FILE name='JKFLIPFLOP' type='XML'>
<SEE_ALSO>
<SEE_ALSO_ITEM><LINK>DLATCH</LINK></SEE_ALSO_ITEM>
<SEE_ALSO_ITEM><LINK>DFLIPFLOP</LINK></SEE_ALSO_ITEM>
<SEE_ALSO_ITEM><LINK>SRFLIPFLOP</LINK></SEE_ALSO_ITEM>
</SEE_ALSO>
</FILE>

<FILE name='Keyboard_shortcuts' type='XML'>
<SEE_ALSO>

</SEE_ALSO>
</FILE>

<FILE name='LOGBLK_f' type='XML'>
<SEE_ALSO>

</SEE_ALSO>
</FILE>

<FILE name='LOGIC' type='XML'>
<SEE_ALSO>
<SEE_ALSO_ITEM><LINK>SRFLIPFLOP</LINK></SEE_ALSO_ITEM>
<SEE_ALSO_ITEM><LINK>JKFLIPFLOP</LINK></SEE_ALSO_ITEM>
</SEE_ALSO>
</FILE>

<FILE name='LOGICAL_OP' type='XML'>
<SEE_ALSO>



</SEE_ALSO>
</FILE>

<FILE name='LOOKUP_f' type='XML'>
<SEE_ALSO>



</SEE_ALSO>
</FILE>

<FILE name='Linear_pal' type='XML'>
<SEE_ALSO>



</SEE_ALSO>
</FILE>

<FILE name='Lorentz_diagr' type='XML'>
  <SEE_ALSO>

  </SEE_ALSO>
</FILE>

<FILE name='MATBKSL' type='XML'>
<SEE_ALSO>
<SEE_ALSO_ITEM><LINK>MATDIV</LINK></SEE_ALSO_ITEM>
<SEE_ALSO_ITEM><LINK>MATMUL</LINK></SEE_ALSO_ITEM>
</SEE_ALSO>
</FILE>

<FILE name='MATCATH' type='XML'>
<SEE_ALSO>
<SEE_ALSO_ITEM><LINK>MATCATV</LINK></SEE_ALSO_ITEM>
</SEE_ALSO>
</FILE>

<FILE name='MATCATV' type='XML'>
<SEE_ALSO>
<SEE_ALSO_ITEM><LINK>MATCATH</LINK></SEE_ALSO_ITEM>
</SEE_ALSO>
</FILE>

<FILE name='MATDET' type='XML'>
<SEE_ALSO>
<SEE_ALSO_ITEM><LINK>MATINV</LINK></SEE_ALSO_ITEM>
</SEE_ALSO>
</FILE>

<FILE name='MATDIAG' type='XML'>
<SEE_ALSO>
<SEE_ALSO_ITEM> <LINK>EXTTRI</LINK> </SEE_ALSO_ITEM>
</SEE_ALSO>
</FILE>

<FILE name='MATDIV' type='XML'>
<SEE_ALSO>
<SEE_ALSO_ITEM> <LINK>MATBKSL</LINK> </SEE_ALSO_ITEM>
<SEE_ALSO_ITEM> <LINK>MATMUL</LINK> </SEE_ALSO_ITEM>
</SEE_ALSO>
</FILE>

<FILE name='MATEIG' type='XML'>
<SEE_ALSO>
<SEE_ALSO_ITEM> <LINK>MATSING</LINK> </SEE_ALSO_ITEM>
</SEE_ALSO>
</FILE>

<FILE name='MATEXPM' type='XML'>
<SEE_ALSO>
<SEE_ALSO_ITEM> <LINK>MATMUL</LINK> </SEE_ALSO_ITEM>
</SEE_ALSO>
</FILE>

<FILE name='MATINV' type='XML'>
<SEE_ALSO>
<SEE_ALSO_ITEM> <LINK>MATLU</LINK> </SEE_ALSO_ITEM>
<SEE_ALSO_ITEM> <LINK>MATPINV</LINK> </SEE_ALSO_ITEM>
</SEE_ALSO>
</FILE>

<FILE name='MATLU' type='XML'>
<SEE_ALSO>
<SEE_ALSO_ITEM> <LINK>MATINV</LINK> </SEE_ALSO_ITEM>
</SEE_ALSO>
</FILE>

<FILE name='MATMAGPHI' type='XML'>
<SEE_ALSO>
<SEE_ALSO_ITEM>
<LINK>MATZREIM</LINK>
</SEE_ALSO_ITEM>
</SEE_ALSO>
</FILE>

<FILE name='MATMUL' type='XML'>
<SEE_ALSO>
<SEE_ALSO_ITEM> <LINK>INTMUL</LINK> </SEE_ALSO_ITEM>
<SEE_ALSO_ITEM> <LINK>MATDIV</LINK> </SEE_ALSO_ITEM>
<SEE_ALSO_ITEM> <LINK>MATBKSL</LINK> </SEE_ALSO_ITEM>
<SEE_ALSO_ITEM> <LINK>MATEXPM</LINK> </SEE_ALSO_ITEM>
<SEE_ALSO_ITEM> <LINK>SUMMATION</LINK> </SEE_ALSO_ITEM>
</SEE_ALSO>
</FILE>

<FILE name='MATPINV' type='XML'>
<SEE_ALSO>
<SEE_ALSO_ITEM> <LINK>MATINV</LINK> </SEE_ALSO_ITEM>
<SEE_ALSO_ITEM> <LINK>MATSING</LINK> </SEE_ALSO_ITEM>
</SEE_ALSO>
</FILE>

<FILE name='MATRESH' type='XML'>
<SEE_ALSO>
<SEE_ALSO_ITEM><LINK>EXTRACT</LINK></SEE_ALSO_ITEM>
</SEE_ALSO>
</FILE>

<FILE name='MATSING' type='XML'>
<SEE_ALSO>
<SEE_ALSO_ITEM> <LINK>MATEIG</LINK> </SEE_ALSO_ITEM>
<SEE_ALSO_ITEM> <LINK>MATLU</LINK> </SEE_ALSO_ITEM>
</SEE_ALSO>
</FILE>

<FILE name='MATSUM' type='XML'>
<SEE_ALSO>
<SEE_ALSO_ITEM><LINK>SUBMAT</LINK></SEE_ALSO_ITEM>
<SEE_ALSO_ITEM><LINK>SUMMATION</LINK></SEE_ALSO_ITEM>
</SEE_ALSO>
</FILE>

<FILE name='MATTRAN' type='XML'>
<SEE_ALSO>
<SEE_ALSO_ITEM><LINK>Matrix_pal</LINK></SEE_ALSO_ITEM>
</SEE_ALSO>
</FILE>

<FILE name='MATZCONJ' type='XML'>
<SEE_ALSO>
<SEE_ALSO_ITEM><LINK>Matrix_pal</LINK></SEE_ALSO_ITEM>
</SEE_ALSO>
</FILE>

<FILE name='MATZREIM' type='XML'>
<SEE_ALSO>
<SEE_ALSO_ITEM><LINK>MATMAGPHI</LINK></SEE_ALSO_ITEM>
</SEE_ALSO>
</FILE>

<FILE name='MAXMIN' type='XML'>
<SEE_ALSO>



</SEE_ALSO>
</FILE>

<FILE name='MAX_f' type='XML'>
<SEE_ALSO>

</SEE_ALSO>
</FILE>

<FILE name='MBLOCK' type='XML'>
<SEE_ALSO>

</SEE_ALSO>
</FILE>

<FILE name='MCLOCK_f' type='XML'>
<SEE_ALSO>

</SEE_ALSO>
</FILE>

<FILE name='MEMORY_f' type='XML'>
<SEE_ALSO>

</SEE_ALSO>
</FILE>

<FILE name='MFCLCK_f' type='XML'>
<SEE_ALSO>

</SEE_ALSO>
</FILE>

<FILE name='MIN_f' type='XML'>
<SEE_ALSO>

</SEE_ALSO>
</FILE>

<FILE name='MOTOR' type='XML'>
<SEE_ALSO>

</SEE_ALSO>
</FILE>

<FILE name='MUX' type='XML'>
<SEE_ALSO>



</SEE_ALSO>
</FILE>

<FILE name='MUX_f' type='XML'>
<SEE_ALSO>

</SEE_ALSO>
</FILE>

<FILE name='M_SWITCH' type='XML'>
<SEE_ALSO>



</SEE_ALSO>
</FILE>

<FILE name='M_freq' type='XML'>
<SEE_ALSO>
<SEE_ALSO_ITEM><LINK>MFCLCK_f</LINK></SEE_ALSO_ITEM>
</SEE_ALSO>
</FILE>

<FILE name='Matrix_pal' type='XML'>
<SEE_ALSO>

</SEE_ALSO>
</FILE>

<FILE name='Menu_entries' type='XML'>
<SEE_ALSO>

</SEE_ALSO>
</FILE>

<FILE name='Modulo_Count' type='XML'>
<SEE_ALSO>

</SEE_ALSO>
</FILE>

<FILE name='Multiwindow' type='XML'>
  <SEE_ALSO>

  </SEE_ALSO>
</FILE>

<FILE name='NEGTOPOS_f' type='XML'>
<SEE_ALSO>

</SEE_ALSO>
</FILE>

<FILE name='NMOS' type='XML'>
<SEE_ALSO>
<SEE_ALSO_ITEM> <LINK>PMOS</LINK> </SEE_ALSO_ITEM>
</SEE_ALSO>
</FILE>

<FILE name='NPN' type='XML'>
<SEE_ALSO>
<SEE_ALSO_ITEM> <LINK>PNP</LINK> </SEE_ALSO_ITEM>
</SEE_ALSO>
</FILE>

<FILE name='NRMSOM_f' type='XML'>
<SEE_ALSO>

</SEE_ALSO>
</FILE>

<FILE name='Non_linear_pal' type='XML'>
<SEE_ALSO>

</SEE_ALSO>
</FILE>

<FILE name='OUTIMPL_f' type='XML'>
<SEE_ALSO>

</SEE_ALSO>
</FILE>

<FILE name='OUT_f' type='XML'>
<SEE_ALSO>

</SEE_ALSO>
</FILE>

<FILE name='OldBlocks_pal' type='XML'>
<SEE_ALSO>

</SEE_ALSO>
</FILE>

<FILE name='OpAmp' type='XML'>
  <SEE_ALSO>

  </SEE_ALSO>
</FILE>

<FILE name='Others_pal' type='XML'>
<SEE_ALSO>

</SEE_ALSO>
</FILE>

<FILE name='PDE' type='XML'>
<SEE_ALSO>

</SEE_ALSO>
</FILE>

<FILE name='PID' type='XML'>
<SEE_ALSO>

</SEE_ALSO>
</FILE>

<FILE name='PMOS' type='XML'>
<SEE_ALSO>
<SEE_ALSO_ITEM> <LINK>NMOS</LINK></SEE_ALSO_ITEM>
</SEE_ALSO>
</FILE>

<FILE name='PNP' type='XML'>
<SEE_ALSO>
<SEE_ALSO_ITEM> <LINK>NPN</LINK> </SEE_ALSO_ITEM>
</SEE_ALSO>
</FILE>

<FILE name='POSTONEG_f' type='XML'>
<SEE_ALSO>

</SEE_ALSO>
</FILE>

<FILE name='POWBLK_f' type='XML'>
<SEE_ALSO>

</SEE_ALSO>
</FILE>

<FILE name='PRODUCT' type='XML'>
<SEE_ALSO>

</SEE_ALSO>
</FILE>

<FILE name='PROD_f' type='XML'>
<SEE_ALSO>

</SEE_ALSO>
</FILE>

<FILE name='PerteDP' type='XML'>
<SEE_ALSO>

</SEE_ALSO>
</FILE>

<FILE name='PotentialSensor' type='XML'>
<SEE_ALSO>



</SEE_ALSO>
</FILE>

<FILE name='PuitsP' type='XML'>
<SEE_ALSO>



</SEE_ALSO>
</FILE>

<FILE name='QUANT_f' type='XML'>
<SEE_ALSO>



</SEE_ALSO>
</FILE>

<FILE name='RAMP' type='XML'>
<SEE_ALSO>



</SEE_ALSO>
</FILE>

<FILE name='RAND_f' type='XML'>
<SEE_ALSO>



</SEE_ALSO>
</FILE>

<FILE name='RAND_m' type='XML'>
<SEE_ALSO>

</SEE_ALSO>
</FILE>

<FILE name='RATELIMITER' type='XML'>
<SEE_ALSO>



</SEE_ALSO>
</FILE>

<FILE name='READAU_f' type='XML'>
<SEE_ALSO>



</SEE_ALSO>
</FILE>

<FILE name='READC_f' type='XML'>
<SEE_ALSO>



</SEE_ALSO>
</FILE>

<FILE name='REGISTER' type='XML'>
<SEE_ALSO>

</SEE_ALSO>
</FILE>

<FILE name='REGISTER_f' type='XML'>
<SEE_ALSO>



</SEE_ALSO>
</FILE>

<FILE name='RELATIONALOP' type='XML'>
<SEE_ALSO>



</SEE_ALSO>
</FILE>

<FILE name='RELAY_f' type='XML'>
<SEE_ALSO>



</SEE_ALSO>
</FILE>

<FILE name='RFILE' type='XML'>
<SEE_ALSO>

</SEE_ALSO>
</FILE>

<FILE name='RFILE_f' type='XML'>
<SEE_ALSO>



</SEE_ALSO>
</FILE>

<FILE name='RICC' type='XML'>
<SEE_ALSO>
<SEE_ALSO_ITEM><LINK>Matrix_pal</LINK></SEE_ALSO_ITEM>
</SEE_ALSO>
</FILE>

<FILE name='ROOTCOEF' type='XML'>
<SEE_ALSO>

</SEE_ALSO>
</FILE>

<FILE name='Resistor' type='XML'>
<SEE_ALSO>



</SEE_ALSO>
</FILE>

<FILE name='SAMPHOLD' type='XML'>
<SEE_ALSO>

</SEE_ALSO>
</FILE>

<FILE name='SAMPHOLD_m' type='XML'>
<SEE_ALSO>

</SEE_ALSO>
</FILE>

<FILE name='SAMPLEHOLD_f' type='XML'>
<SEE_ALSO>



</SEE_ALSO>
</FILE>

<FILE name='SATURATION' type='XML'>
<SEE_ALSO>



</SEE_ALSO>
</FILE>

<FILE name='SAT_f' type='XML'>
<SEE_ALSO>

</SEE_ALSO>
</FILE>

<FILE name='SAWTOOTH_f' type='XML'>
<SEE_ALSO>



</SEE_ALSO>
</FILE>

<FILE name='SCALAR2VECTOR' type='XML'>
<SEE_ALSO>



</SEE_ALSO>
</FILE>

<FILE name='SELECT_f' type='XML'>
<SEE_ALSO>



</SEE_ALSO>
</FILE>

<FILE name='SELECT_m' type='XML'>
<SEE_ALSO>

</SEE_ALSO>
</FILE>

<FILE name='SHIFT' type='XML'>
<SEE_ALSO>
<SEE_ALSO_ITEM> <LINK>BITSET</LINK> </SEE_ALSO_ITEM>
<SEE_ALSO_ITEM> <LINK>BITCLEAR</LINK> </SEE_ALSO_ITEM>
</SEE_ALSO>
</FILE>

<FILE name='SIGNUM' type='XML'>
<SEE_ALSO>



</SEE_ALSO>
</FILE>

<FILE name='SINBLK_f' type='XML'>
<SEE_ALSO>

</SEE_ALSO>
</FILE>

<FILE name='SLIDER_f' type='XML'>
<SEE_ALSO>

</SEE_ALSO>
</FILE>

<FILE name='SPLIT_f' type='XML'>
<SEE_ALSO>

</SEE_ALSO>
</FILE>

<FILE name='SQRT' type='XML'>
<SEE_ALSO>
<SEE_ALSO_ITEM> <LINK>POWBLK_f</LINK> </SEE_ALSO_ITEM>
</SEE_ALSO>
</FILE>

<FILE name='SRFLIPFLOP' type='XML'>
<SEE_ALSO>
<SEE_ALSO_ITEM><LINK>DLATCH</LINK></SEE_ALSO_ITEM>
<SEE_ALSO_ITEM><LINK>DFLIPFLOP</LINK></SEE_ALSO_ITEM>
<SEE_ALSO_ITEM><LINK>JKFLIPFLOP</LINK></SEE_ALSO_ITEM>
</SEE_ALSO>
</FILE>

<FILE name='STEP' type='XML'>
<SEE_ALSO>

</SEE_ALSO>
</FILE>

<FILE name='STEP_FUNCTION' type='XML'>
<SEE_ALSO>



</SEE_ALSO>
</FILE>

<FILE name='SUBMAT' type='XML'>
<SEE_ALSO>

</SEE_ALSO>
</FILE>

<FILE name='SUMMATION' type='XML'>
<SEE_ALSO>

</SEE_ALSO>
</FILE>

<FILE name='SUM_f' type='XML'>
<SEE_ALSO>



</SEE_ALSO>
</FILE>

<FILE name='SUPER_f' type='XML'>
<SEE_ALSO>



</SEE_ALSO>
</FILE>

<FILE name='SWITCH2' type='XML'>
<SEE_ALSO>



</SEE_ALSO>
</FILE>

<FILE name='SWITCH2_m' type='XML'>
<SEE_ALSO>

</SEE_ALSO>
</FILE>

<FILE name='SWITCH_f' type='XML'>
<SEE_ALSO>



</SEE_ALSO>
</FILE>

<FILE name='SampleCLK' type='XML'>
<SEE_ALSO>
<SEE_ALSO_ITEM><LINK>CLOCK_c</LINK></SEE_ALSO_ITEM>
<SEE_ALSO_ITEM><LINK>Counter</LINK></SEE_ALSO_ITEM>
<SEE_ALSO_ITEM><LINK>ESELECT_f</LINK></SEE_ALSO_ITEM>
<SEE_ALSO_ITEM><LINK>M_freq</LINK></SEE_ALSO_ITEM>
</SEE_ALSO>
</FILE>

<FILE name='Sigbuilder' type='XML'>
<SEE_ALSO>

</SEE_ALSO>
</FILE>

<FILE name='SineVoltage' type='XML'>
<SEE_ALSO>

</SEE_ALSO>
</FILE>

<FILE name='Sinks_pal' type='XML'>
<SEE_ALSO>



</SEE_ALSO>
</FILE>

<FILE name='SourceP' type='XML'>
<SEE_ALSO>



</SEE_ALSO>
</FILE>

<FILE name='Sources_pal' type='XML'>
<SEE_ALSO>



</SEE_ALSO>
</FILE>

<FILE name='Switch' type='XML'>
  <SEE_ALSO>

  </SEE_ALSO>
</FILE>

<FILE name='TANBLK_f' type='XML'>
<SEE_ALSO>

</SEE_ALSO>
</FILE>

<FILE name='TCLSS' type='XML'>
<SEE_ALSO>

</SEE_ALSO>
</FILE>

<FILE name='TCLSS_f' type='XML'>
<SEE_ALSO>



</SEE_ALSO>
</FILE>

<FILE name='TEXT_f' type='XML'>
<SEE_ALSO>



</SEE_ALSO>
</FILE>

<FILE name='TIME_DELAY' type='XML'>
<SEE_ALSO>

</SEE_ALSO>
</FILE>

<FILE name='TIME_f' type='XML'>
<SEE_ALSO>

</SEE_ALSO>
</FILE>

<FILE name='TKSCALE' type='XML'>
  <SEE_ALSO>

  </SEE_ALSO>
</FILE>

<FILE name='TOWS_c' type='XML'>
  <SEE_ALSO>
  <SEE_ALSO_ITEM><LINK>FROMWS_c</LINK></SEE_ALSO_ITEM>
  </SEE_ALSO>
</FILE>

<FILE name='TRASH_f' type='XML'>
<SEE_ALSO>

</SEE_ALSO>
</FILE>

<FILE name='ThermoHydraulics_pal' type='XML'>
<SEE_ALSO>

</SEE_ALSO>
</FILE>

<FILE name='Threshold_pal' type='XML'>
<SEE_ALSO>

</SEE_ALSO>
</FILE>

<FILE name='TrigFun' type='XML'>
<SEE_ALSO>

</SEE_ALSO>
</FILE>

<FILE name='VARIABLE_DELAY' type='XML'>
<SEE_ALSO>



</SEE_ALSO>
</FILE>

<FILE name='VVsourceAC' type='XML'>
<SEE_ALSO>



</SEE_ALSO>
</FILE>

<FILE name='VanneReglante' type='XML'>
<SEE_ALSO>



</SEE_ALSO>
</FILE>

<FILE name='VariableResistor' type='XML'>
<SEE_ALSO>



</SEE_ALSO>
</FILE>

<FILE name='VoltageSensor' type='XML'>
<SEE_ALSO>



</SEE_ALSO>
</FILE>

<FILE name='VsourceAC' type='XML'>
<SEE_ALSO>



</SEE_ALSO>
</FILE>

<FILE name='WFILE' type='XML'>
<SEE_ALSO>

</SEE_ALSO>
</FILE>

<FILE name='WFILE_f' type='XML'>
<SEE_ALSO>



</SEE_ALSO>
</FILE>

<FILE name='WRITEAU_f' type='XML'>
<SEE_ALSO>



</SEE_ALSO>
</FILE>

<FILE name='WRITEC_f' type='XML'>
<SEE_ALSO>



</SEE_ALSO>
</FILE>

<FILE name='ZCROSS_f' type='XML'>
<SEE_ALSO>



</SEE_ALSO>
</FILE>

<FILE name='block_type' type='XML'>
  <SEE_ALSO>

  </SEE_ALSO>
</FILE>

<FILE name='buildouttb' type='XML'>
<SEE_ALSO>

</SEE_ALSO>
</FILE>

<FILE name='c_block' type='XML'>
<SEE_ALSO>



</SEE_ALSO>
</FILE>

<FILE name='create_palette' type='XML'>
  <SEE_ALSO>

  </SEE_ALSO>
</FILE>

<FILE name='curblock' type='XML'>
<SEE_ALSO>

</SEE_ALSO>
</FILE>

<FILE name='data_type' type='XML'>
  <SEE_ALSO>

  </SEE_ALSO>
</FILE>

<FILE name='fortran_block' type='XML'>
<SEE_ALSO>



</SEE_ALSO>
</FILE>

<FILE name='freq_div' type='XML'>
<SEE_ALSO>

</SEE_ALSO>
</FILE>

<FILE name='func_block' type='XML'>
<SEE_ALSO>

</SEE_ALSO>
</FILE>

<FILE name='generic_block' type='XML'>
<SEE_ALSO>

</SEE_ALSO>
</FILE>

<FILE name='generic_block2' type='XML'>
<SEE_ALSO>

</SEE_ALSO>
</FILE>

<FILE name='generic_block3' type='XML'>
<SEE_ALSO>

</SEE_ALSO>
</FILE>

<FILE name='get_scicos_version' type='XML'>
  <SEE_ALSO>

  </SEE_ALSO>
</FILE>

<FILE name='getblocklabel' type='XML'>
  <SEE_ALSO>

  </SEE_ALSO>
</FILE>

<FILE name='getscicosvars' type='XML'>
  <SEE_ALSO>
    <SEE_ALSO_ITEM><LINK>DEBUG_SCICOS</LINK></SEE_ALSO_ITEM>
  </SEE_ALSO>
</FILE>

<FILE name='lincos' type='XML'>
<SEE_ALSO>
<SEE_ALSO_ITEM><A href="steadycos.htm">steadycos</A></SEE_ALSO_ITEM>
<SEE_ALSO_ITEM><A href="scicos_simulate.htm">scicos_simulate</A></SEE_ALSO_ITEM>
</SEE_ALSO>
</FILE>

<FILE name='phase_simulation' type='XML'>
  <SEE_ALSO>

  </SEE_ALSO>
</FILE>

<FILE name='pointer_xproperty' type='XML'>
  <SEE_ALSO>
  <SEE_ALSO_ITEM> <LINK>set_xproperty</LINK> </SEE_ALSO_ITEM>
  </SEE_ALSO>
</FILE>

<FILE name='sci_struct' type='XML'>
  <SEE_ALSO>

  </SEE_ALSO>
</FILE>

<FILE name='scicos' type='XML'>
<SEE_ALSO>
<SEE_ALSO_ITEM><A href="scicosim.htm">scicosim</A></SEE_ALSO_ITEM>
<SEE_ALSO_ITEM><A href="scicos_simulate.htm">scicos_simulate</A></SEE_ALSO_ITEM>
</SEE_ALSO>
</FILE>

<FILE name='scicos_block' type='XML'>
  <SEE_ALSO>

  </SEE_ALSO>
</FILE>

<FILE name='scicos_block4_rout' type='XML'>
  <SEE_ALSO>

  </SEE_ALSO>
</FILE>

<FILE name='scicos_cpr' type='XML'>
  <SEE_ALSO>

  </SEE_ALSO>
</FILE>

<FILE name='scicos_debug' type='XML'>
  <SEE_ALSO>
    <SEE_ALSO_ITEM><LINK>DEBUG_SCICOS</LINK></SEE_ALSO_ITEM>
  </SEE_ALSO>
</FILE>

<FILE name='scicos_diagram' type='XML'>
<SEE_ALSO>

</SEE_ALSO>
</FILE>

<FILE name='scicos_graphics' type='XML'>
<SEE_ALSO>

</SEE_ALSO>
</FILE>

<FILE name='scicos_link' type='XML'>
<SEE_ALSO>

</SEE_ALSO>
</FILE>

<FILE name='scicos_model' type='XML'>
<SEE_ALSO>

</SEE_ALSO>
</FILE>

<FILE name='scicos_params' type='XML'>
<SEE_ALSO>

</SEE_ALSO>
</FILE>

<FILE name='scicos_sim' type='XML'>
<SEE_ALSO>

</SEE_ALSO>
</FILE>

<FILE name='scicos_simulate' type='XML'>
<SEE_ALSO>
<SEE_ALSO_ITEM><A href="scicosim.htm">scicosim</A></SEE_ALSO_ITEM>
<SEE_ALSO_ITEM><A href="scicos.htm">scicos</A></SEE_ALSO_ITEM>
<SEE_ALSO_ITEM><A href="steadycos.htm">steadycos</A></SEE_ALSO_ITEM>
<SEE_ALSO_ITEM><A href="lincos.htm">lincos</A></SEE_ALSO_ITEM>
</SEE_ALSO>
</FILE>

<FILE name='scicos_state' type='XML'>
<SEE_ALSO>

</SEE_ALSO>
</FILE>

<FILE name='scicos_time' type='XML'>
<SEE_ALSO>

</SEE_ALSO>
</FILE>

<FILE name='scicosim' type='XML'>
<SEE_ALSO>
<SEE_ALSO_ITEM><A href="scicos_simulate.htm">scicos_simulate</A></SEE_ALSO_ITEM>
<SEE_ALSO_ITEM><A href="scicos.htm">scicos</A></SEE_ALSO_ITEM>
</SEE_ALSO>
</FILE>

<FILE name='scifunc_block' type='XML'>
<SEE_ALSO>

</SEE_ALSO>
</FILE>

<FILE name='scifunc_block_m' type='XML'>
<SEE_ALSO>

</SEE_ALSO>
</FILE>

<FILE name='set_blockerror' type='XML'>
  <SEE_ALSO>

  </SEE_ALSO>
</FILE>

<FILE name='set_xproperty' type='XML'>
  <SEE_ALSO>
  <SEE_ALSO_ITEM> <LINK>pointer_xproperty</LINK> </SEE_ALSO_ITEM>
  </SEE_ALSO>
</FILE>

<FILE name='steadycos' type='XML'>
<SEE_ALSO>
<SEE_ALSO_ITEM><A href="lincos.htm">lincos</A></SEE_ALSO_ITEM>
<SEE_ALSO_ITEM><A href="scicos_simulate.htm">scicos_simulate</A></SEE_ALSO_ITEM>
<SEE_ALSO_ITEM><A href="scicos.htm">scicos</A></SEE_ALSO_ITEM>
</SEE_ALSO>
</FILE>

<FILE name='use_flag' type='XML'>
  <SEE_ALSO>

  </SEE_ALSO>
</FILE>

<FILE name='var2vec' type='XML'>
<SEE_ALSO>
<SEE_ALSO_ITEM><A href="vec2var.htm">vec2var</A></SEE_ALSO_ITEM>
</SEE_ALSO>
</FILE>

<FILE name='vec2var' type='XML'>
<SEE_ALSO>
<SEE_ALSO_ITEM><A href="var2vec.htm">var2vec</A></SEE_ALSO_ITEM>
</SEE_ALSO>
</FILE>


</DATA>
