<?xml version="1.0" encoding="ISO-8859-1" standalone="no"?>
<!DOCTYPE MAN SYSTEM "../../manrev.dtd">
<MAN>
  <LANGUAGE>eng</LANGUAGE>
  <TITLE>findm</TITLE>
  <TYPE>Scilab Function</TYPE>
  <DATE>April 1993</DATE>
  <SHORT_DESCRIPTION name="findm"> for elliptic filter design</SHORT_DESCRIPTION>
  <CALLING_SEQUENCE>
    <CALLING_SEQUENCE_ITEM>[m]=findm(chi)  </CALLING_SEQUENCE_ITEM>
  </CALLING_SEQUENCE>
  <DESCRIPTION>
    <P>
    Search for <VERB>m</VERB> such that <VERB>chi = %k(1-m)/%k(m)</VERB>
    (For use with <VERB>find_freq</VERB>).</P>
  </DESCRIPTION>
  <SEE_ALSO>
    <SEE_ALSO_ITEM>
      <LINK>%k</LINK>
    </SEE_ALSO_ITEM>
  </SEE_ALSO>
  <AUTHOR>F. D.;   </AUTHOR>
</MAN>
