<?xml version="1.0" encoding="ISO-8859-1" standalone="no"?>
<!DOCTYPE MAN SYSTEM "../../manrev.dtd">
<MAN>
  <LANGUAGE>eng</LANGUAGE>
  <TITLE>xinfo</TITLE>
  <TYPE>Scilab Function</TYPE>
  <DATE>April 1993</DATE>
  <SHORT_DESCRIPTION name="xinfo"> draw an info string in the message subwindow</SHORT_DESCRIPTION>
  <CALLING_SEQUENCE>
    <CALLING_SEQUENCE_ITEM>xinfo(info)  </CALLING_SEQUENCE_ITEM>
  </CALLING_SEQUENCE>
  <PARAM>
    <PARAM_INDENT>
      <PARAM_ITEM>
        <PARAM_NAME>info</PARAM_NAME>
        <PARAM_DESCRIPTION>
          <SP>: string</SP>
        </PARAM_DESCRIPTION>
      </PARAM_ITEM>
    </PARAM_INDENT>
  </PARAM>
  <DESCRIPTION>
    <P><VERB>xinfo</VERB> draws the string <VERB>info</VERB> in the message subwindow
    of the current graphics window.</P>
  </DESCRIPTION>
</MAN>
